IBLPy/__init__.py
IBLPy/classes.py
IBLPy/config.py
IBLPy/http.py
IBLPy/main.py
IBLPy/ws.py
IBLPy-2.0.9.dist-info/LICENSE
IBLPy-2.0.9.dist-info/METADATA
IBLPy-2.0.9.dist-info/WHEEL
IBLPy-2.0.9.dist-info/top_level.txt
IBLPy-2.0.9.dist-info/RECORD
