Metadata-Version: 2.1
Name: IBLPy
Version: 2.0.9
Summary: IBLPy is a API Wrapper for Infinity Bots
Home-page: https://github.com/cheesycod/IBLPy
Author: Rootspring
Author-email: tor_needletail@outlook.com
License: MIT
Project-URL: Bug Tracker, https://github.com/cheesycod/IBLPy/issues
Platform: UNKNOWN
Classifier: Programming Language :: Python :: 3
Classifier: License :: OSI Approved :: MIT License
Classifier: Operating System :: OS Independent
License-File: LICENSE
Requires-Dist: aiohttp
Requires-Dist: loguru
Requires-Dist: discord
